{"tableList":[{"name":"auto_test","javaClassName":"Auto_test","columns":[{"name":"ID","javaFieldName":"ID","jdbcType":"INTEGER","autoIncrement":true,"primaryKey":true,"length":10,"isNull":false,"precision":0,"gen_generate":false,"gen_generateAsQuery":false,"gen_dataType":"INT","gen_title":"","gen_memo":"","gen_require":false,"gen_min":-2147483648,"gen_max":2147483647,"gen_precision":null},{"name":"col1","javaFieldName":"col1","jdbcType":"NVARCHAR","autoIncrement":false,"primaryKey":false,"length":50,"isNull":true,"precision":0,"gen_generate":true,"gen_generateAsQuery":false,"gen_dataType":"STRING","gen_title":"","gen_memo":"","gen_require":false,"gen_min":0,"gen_max":50,"gen_precision":null},{"name":"col2","javaFieldName":"col2","jdbcType":"INTEGER","autoIncrement":false,"primaryKey":false,"length":10,"isNull":true,"precision":0,"gen_generate":true,"gen_generateAsQuery":false,"gen_dataType":"INT","gen_title":"","gen_memo":"","gen_require":false,"gen_min":-2147483648,"gen_max":2147483647,"gen_precision":null},{"name":"c1","javaFieldName":"c1","jdbcType":"NVARCHAR","autoIncrement":false,"primaryKey":false,"length":50,"isNull":true,"precision":0,"gen_generate":true,"gen_generateAsQuery":false,"gen_dataType":"STRING","gen_title":"","gen_memo":"","gen_require":false,"gen_min":0,"gen_max":50,"gen_precision":null},{"name":"c2","javaFieldName":"c2","jdbcType":"BIGINT","autoIncrement":false,"primaryKey":false,"length":19,"isNull":true,"precision":0,"gen_generate":true,"gen_generateAsQuery":false,"gen_dataType":"LONGINT","gen_title":"","gen_memo":"","gen_require":false,"gen_min":-9223372036854775808,"gen_max":9223372036854775807,"gen_precision":null},{"name":"c6","javaFieldName":"c6","jdbcType":"DECIMAL","autoIncrement":false,"primaryKey":false,"length":19,"isNull":true,"precision":4,"gen_generate":true,"gen_generateAsQuery":false,"gen_dataType":"DECIMAL","gen_title":"","gen_memo":"","gen_require":false,"gen_min":-999999999999999,"gen_max":999999999999999,"gen_precision":4},{"name":"c8","javaFieldName":"c8","jdbcType":"NCHAR","autoIncrement":false,"primaryKey":false,"length":10,"isNull":true,"precision":0,"gen_generate":true,"gen_generateAsQuery":false,"gen_dataType":"STRING","gen_title":"","gen_memo":"","gen_require":false,"gen_min":0,"gen_max":10,"gen_precision":null},{"name":"c10","javaFieldName":"c10","jdbcType":"DATE","autoIncrement":false,"primaryKey":false,"length":10,"isNull":true,"precision":0,"gen_generate":true,"gen_generateAsQuery":false,"gen_dataType":"DATE","gen_title":"","gen_memo":"","gen_require":false,"gen_min":null,"gen_max":null,"gen_precision":null},{"name":"c11","javaFieldName":"c11","jdbcType":"TIME","autoIncrement":false,"primaryKey":false,"length":16,"isNull":true,"precision":7,"gen_generate":true,"gen_generateAsQuery":false,"gen_dataType":"TIME","gen_title":"","gen_memo":"","gen_require":false,"gen_min":null,"gen_max":null,"gen_precision":null},{"name":"c12","javaFieldName":"c12","jdbcType":"TIMESTAMP","autoIncrement":false,"primaryKey":false,"length":23,"isNull":true,"precision":3,"gen_generate":true,"gen_generateAsQuery":false,"gen_dataType":"DATETIME","gen_title":"","gen_memo":"","gen_require":false,"gen_min":null,"gen_max":null,"gen_precision":null},{"name":"c13","javaFieldName":"c13","jdbcType":"TIMESTAMP","autoIncrement":false,"primaryKey":false,"length":16,"isNull":true,"precision":0,"gen_generate":true,"gen_generateAsQuery":false,"gen_dataType":"DATETIME","gen_title":"","gen_memo":"","gen_require":false,"gen_min":null,"gen_max":null,"gen_precision":null},{"name":"c14","javaFieldName":"c14","jdbcType":"SMALLINT","autoIncrement":false,"primaryKey":false,"length":5,"isNull":true,"precision":0,"gen_generate":true,"gen_generateAsQuery":false,"gen_dataType":"INT","gen_title":"","gen_memo":"","gen_require":false,"gen_min":-32768,"gen_max":32767,"gen_precision":null},{"name":"c15","javaFieldName":"c15","jdbcType":"TINYINT","autoIncrement":false,"primaryKey":false,"length":3,"isNull":true,"precision":0,"gen_generate":true,"gen_generateAsQuery":false,"gen_dataType":"INT","gen_title":"","gen_memo":"","gen_require":false,"gen_min":-128,"gen_max":127,"gen_precision":null},{"name":"c17","javaFieldName":"c17","jdbcType":"NCHAR","autoIncrement":false,"primaryKey":false,"length":10,"isNull":true,"precision":0,"gen_generate":true,"gen_generateAsQuery":false,"gen_dataType":"STRING","gen_title":"","gen_memo":"","gen_require":false,"gen_min":0,"gen_max":10,"gen_precision":null},{"name":"c5","javaFieldName":"c5","jdbcType":"LONGNVARCHAR","autoIncrement":false,"primaryKey":false,"length":1073741823,"isNull":true,"precision":0,"gen_generate":true,"gen_generateAsQuery":false,"gen_dataType":"STRING","gen_title":"","gen_memo":"","gen_require":false,"gen_min":0,"gen_max":1073741823,"gen_precision":null},{"name":"c18","javaFieldName":"c18","jdbcType":"DECIMAL","autoIncrement":false,"primaryKey":false,"length":18,"isNull":true,"precision":2,"gen_generate":true,"gen_generateAsQuery":false,"gen_dataType":"DECIMAL","gen_title":"c18","gen_memo":"","gen_require":false,"gen_min":-9999999999999999,"gen_max":9999999999999999,"gen_precision":2}]},{"name":"auto_test_1","javaClassName":"Auto_test_1","columns":[{"name":"Id","javaFieldName":"id","jdbcType":"INTEGER","autoIncrement":true,"primaryKey":true,"length":10,"isNull":false,"precision":0,"gen_generate":false,"gen_generateAsQuery":false,"gen_dataType":"INT","gen_title":"","gen_memo":"","gen_require":false,"gen_min":-2147483648,"gen_max":2147483647,"gen_precision":null},{"name":"c1","javaFieldName":"c1","jdbcType":"NCHAR","autoIncrement":false,"primaryKey":false,"length":10,"isNull":true,"precision":0,"gen_generate":true,"gen_generateAsQuery":false,"gen_dataType":"STRING","gen_title":"c1","gen_memo":"","gen_require":false,"gen_min":0,"gen_max":10,"gen_precision":null},{"name":"c2","javaFieldName":"c2","jdbcType":"INTEGER","autoIncrement":false,"primaryKey":false,"length":10,"isNull":true,"precision":0,"gen_generate":true,"gen_generateAsQuery":false,"gen_dataType":"INT","gen_title":"c2","gen_memo":"","gen_require":false,"gen_min":-2147483648,"gen_max":2147483647,"gen_precision":null},{"name":"c3","javaFieldName":"c3","jdbcType":"NVARCHAR","autoIncrement":false,"primaryKey":false,"length":50,"isNull":true,"precision":0,"gen_generate":true,"gen_generateAsQuery":false,"gen_dataType":"STRING","gen_title":"c3","gen_memo":"","gen_require":false,"gen_min":0,"gen_max":50,"gen_precision":null},{"name":"c4","javaFieldName":"c4","jdbcType":"DATE","autoIncrement":false,"primaryKey":false,"length":10,"isNull":true,"precision":0,"gen_generate":true,"gen_generateAsQuery":false,"gen_dataType":"DATE","gen_title":"c4","gen_memo":"","gen_require":false,"gen_min":null,"gen_max":null,"gen_precision":null},{"name":"c5","javaFieldName":"c5","jdbcType":"TIME","autoIncrement":false,"primaryKey":false,"length":16,"isNull":true,"precision":7,"gen_generate":true,"gen_generateAsQuery":false,"gen_dataType":"TIME","gen_title":"c5","gen_memo":"","gen_require":false,"gen_min":null,"gen_max":null,"gen_precision":null},{"name":"c6","javaFieldName":"c6","jdbcType":"TIMESTAMP","autoIncrement":false,"primaryKey":false,"length":23,"isNull":true,"precision":3,"gen_generate":true,"gen_generateAsQuery":false,"gen_dataType":"DATETIME","gen_title":"c6","gen_memo":"","gen_require":false,"gen_min":null,"gen_max":null,"gen_precision":null},{"name":"c7","javaFieldName":"c7","jdbcType":"DECIMAL","autoIncrement":false,"primaryKey":false,"length":18,"isNull":true,"precision":2,"gen_generate":true,"gen_generateAsQuery":false,"gen_dataType":"DECIMAL","gen_title":"c7","gen_memo":"","gen_require":false,"gen_min":-9999999999999999,"gen_max":9999999999999999,"gen_precision":2},{"name":"c8","javaFieldName":"c8","jdbcType":"LONGNVARCHAR","autoIncrement":false,"primaryKey":false,"length":1073741823,"isNull":true,"precision":0,"gen_generate":true,"gen_generateAsQuery":false,"gen_dataType":"STRING","gen_title":"c8","gen_memo":"","gen_require":false,"gen_min":0,"gen_max":1073741823,"gen_precision":null}]}]}